[
  {
    "items": [
      {
        "product_id": 660,
        "quantity": 4
      }
    ],
    "billing_address": {
      "line_1": "2644 Hermann Loop",
      "city": "West Maeveborough",
      "country": "Estonia",
      "zip": "20756-8235",
      "latitude": 14.8874,
      "longitude": 77.9908
    },
    "shipping_address": {
      "line_1": "947 Geo Cape",
      "city": "East Darwin",
      "country": "Sudan",
      "zip": "34084",
      "latitude": 69.6773,
      "longitude": 102.9497
    }
  },
  {
    "items": [
      {
        "product_id": 678,
        "quantity": 2
      },
      {
        "product_id": 170,
        "quantity": 2
      },
      {
        "product_id": 681,
        "quantity": 2
      },
      {
        "product_id": 2,
        "quantity": 4
      },
      {
        "product_id": 640,
        "quantity": 5
      }
    ],
    "billing_address": {
      "line_1": "68928 Quigley Station",
      "city": "Adahburgh",
      "country": "Russian Federation",
      "zip": "78493",
      "latitude": 89.6931,
      "longitude": -98.5709
    },
    "shipping_address": {
      "line_1": "857 Wisoky Forks",
      "city": "New Deanna",
      "country": "Grenada",
      "zip": "08222",
      "latitude": -18.7654,
      "longitude": -93.5119
    }
  },
  {
    "items": [
      {
        "product_id": 252,
        "quantity": 2
      },
      {
        "product_id": 915,
        "quantity": 4
      },
      {
        "product_id": 550,
        "quantity": 4
      }
    ],
    "billing_address": {
      "line_1": "52526 Hudson Springs",
      "city": "Lake Metaburgh",
      "country": "Syrian Arab Republic",
      "zip": "08980-9709",
      "latitude": -21.2273,
      "longitude": 138.3021
    },
    "shipping_address": {
      "line_1": "2784 Lon Mews",
      "city": "Hoegerport",
      "country": "Faroe Islands",
      "zip": "23989-4320",
      "latitude": 26.8116,
      "longitude": -37.8557
    }
  },
  {
    "items": [
      {
        "product_id": 103,
        "quantity": 5
      },
      {
        "product_id": 680,
        "quantity": 2
      },
      {
        "product_id": 416,
        "quantity": 4
      },
      {
        "product_id": 420,
        "quantity": 1
      },
      {
        "product_id": 411,
        "quantity": 2
      }
    ],
    "billing_address": {
      "line_1": "06661 Travis Center",
      "city": "Lake Cecileville",
      "country": "Switzerland",
      "zip": "82136",
      "latitude": -63.3797,
      "longitude": 76.7276
    },
    "shipping_address": {
      "line_1": "8256 Kamryn Mountains",
      "city": "Lurastad",
      "country": "Micronesia",
      "zip": "43891-8173",
      "latitude": 83.3205,
      "longitude": 175.5562
    }
  },
  {
    "items": [
      {
        "product_id": 37,
        "quantity": 1
      },
      {
        "product_id": 641,
        "quantity": 2
      }
    ],
    "billing_address": {
      "line_1": "4250 Mabelle Trace",
      "city": "Goodwinberg",
      "country": "Sierra Leone",
      "zip": "88119-9358",
      "latitude": 21.2996,
      "longitude": -75.6734
    },
    "shipping_address": {
      "line_1": "61762 Gaylord Plains",
      "city": "Lake Trace",
      "country": "Germany",
      "zip": "75780",
      "latitude": -74.9491,
      "longitude": -41.8779
    }
  },
  {
    "items": [
      {
        "product_id": 966,
        "quantity": 4
      }
    ],
    "billing_address": {
      "line_1": "94614 Laurel Mission",
      "city": "New Milford",
      "country": "El Salvador",
      "zip": "14688",
      "latitude": -10.7047,
      "longitude": -49.3913
    },
    "shipping_address": {
      "line_1": "62830 Dach Drive",
      "city": "Lake Jordihaven",
      "country": "Ukraine",
      "zip": "90802-0104",
      "latitude": -78.4313,
      "longitude": -151.1333
    }
  },
  {
    "items": [
      {
        "product_id": 928,
        "quantity": 4
      }
    ],
    "billing_address": {
      "line_1": "85277 Johnson Highway",
      "city": "Harrisport",
      "country": "Mauritania",
      "zip": "48418-0087",
      "latitude": -70.8634,
      "longitude": -64.2839
    },
    "shipping_address": {
      "line_1": "48424 Ericka Stream",
      "city": "Casimermouth",
      "country": "Bosnia and Herzegovina",
      "zip": "86571-0220",
      "latitude": 29.197,
      "longitude": -63.859
    }
  },
  {
    "items": [
      {
        "product_id": 844,
        "quantity": 1
      },
      {
        "product_id": 828,
        "quantity": 5
      },
      {
        "product_id": 883,
        "quantity": 3
      }
    ],
    "billing_address": {
      "line_1": "82438 Green Mall",
      "city": "Gusikowskiland",
      "country": "Panama",
      "zip": "51248",
      "latitude": -56.5374,
      "longitude": 21.0997
    },
    "shipping_address": {
      "line_1": "303 Obie Gateway",
      "city": "O'Reillyhaven",
      "country": "Kenya",
      "zip": "01194",
      "latitude": -8.1243,
      "longitude": -150.3309
    }
  },
  {
    "items": [
      {
        "product_id": 598,
        "quantity": 1
      },
      {
        "product_id": 641,
        "quantity": 3
      }
    ],
    "billing_address": {
      "line_1": "67493 Luz Bridge",
      "city": "Cruickshankview",
      "country": "Comoros",
      "zip": "08436-1363",
      "latitude": 58.672,
      "longitude": 35.8344
    },
    "shipping_address": {
      "line_1": "6567 Rowe Corners",
      "city": "Port Ludwigville",
      "country": "Kuwait",
      "zip": "26211-5219",
      "latitude": -55.6654,
      "longitude": 129.2181
    }
  },
  {
    "items": [
      {
        "product_id": 335,
        "quantity": 2
      },
      {
        "product_id": 156,
        "quantity": 5
      },
      {
        "product_id": 587,
        "quantity": 3
      },
      {
        "product_id": 976,
        "quantity": 4
      },
      {
        "product_id": 954,
        "quantity": 1
      }
    ],
    "billing_address": {
      "line_1": "3114 Cartwright Mount",
      "city": "Carrollton",
      "country": "Guadeloupe",
      "zip": "74772",
      "latitude": 88.5703,
      "longitude": -79.0126
    },
    "shipping_address": {
      "line_1": "102 Padberg Pass",
      "city": "Reillyberg",
      "country": "Tonga",
      "zip": "91761-5091",
      "latitude": 15.0776,
      "longitude": 115.8023
    }
  }
]